event_streamer_schemas/__init__.py
event_streamer_schemas/abi.py
event_streamer_schemas/api.py
event_streamer_schemas/circuit_breaker.py
event_streamer_schemas/confirmations.py
event_streamer_schemas/events.py
event_streamer_schemas/streaming.py
event_streamer_schemas/subscriptions.py
event_streamer_sdk/__init__.py
event_streamer_sdk/abi_parser.py
event_streamer_sdk/client.py
event_streamer_sdk/exceptions.py
event_streamer_sdk/streaming_client.py
event_streamer_sdk/models/__init__.py
event_streamer_sdk/models/abi.py
event_streamer_sdk/models/circuit_breaker.py
event_streamer_sdk/models/confirmations.py
event_streamer_sdk/models/subscriptions.py
event_streamer_sdk/schemas/__init__.py
event_streamer_sdk/tests/test_abi_parsing.py
event_streamer_sdk-0.5.0.dist-info/METADATA
event_streamer_sdk-0.5.0.dist-info/WHEEL
event_streamer_sdk-0.5.0.dist-info/licenses/LICENSE
event_streamer_sdk-0.5.0.dist-info/RECORD
