Metadata-Version: 2.4
Name: event-streamer-sdk
Version: 0.5.0
Summary: Python SDK for Event Streamer blockchain event monitoring service with HTTP streaming support
Project-URL: Homepage, https://github.com/dcentralab/event-streamer-sdk
Project-URL: Repository, https://github.com/dcentralab/event-streamer-sdk.git
Project-URL: Documentation, https://event-streamer-sdk.readthedocs.io/
Author-email: DcentraLab <contact@dcentralab.com>
License: MIT
License-File: LICENSE
Keywords: blockchain,ethereum,events,monitoring,sdk,streaming
Classifier: Development Status :: 4 - Beta
Classifier: Intended Audience :: Developers
Classifier: License :: OSI Approved :: MIT License
Classifier: Programming Language :: Python :: 3
Classifier: Programming Language :: Python :: 3.11
Classifier: Programming Language :: Python :: 3.12
Classifier: Topic :: Internet :: WWW/HTTP :: HTTP Servers
Classifier: Topic :: Software Development :: Libraries :: Python Modules
Requires-Python: >=3.11
Requires-Dist: aiohttp>=3.8.0
Requires-Dist: eth-typing>=4.0.0
Requires-Dist: pydantic>=2.0.0
Provides-Extra: dev
Requires-Dist: pyright>=1.1.402; extra == 'dev'
Requires-Dist: pytest-asyncio>=0.21.0; extra == 'dev'
Requires-Dist: pytest>=7.0.0; extra == 'dev'
Requires-Dist: ruff>=0.11.3; extra == 'dev'
